Workbook

Sheet How To Use
A1: Monthly Bank Reconciliation Tool
A2: Illustrative sample data for a fictional company. Not from any employer. Built by Tahsin Devrim Mahmud.
A4: PURPOSE: Reconcile the bank statement to the general ledger cash account and surface every reconciling item automatically.
A5: 1. Paste the bank statement into 'Bank Statement' (Date, Reference, Description, Amount). Deposits positive, withdrawals negative.
A6: 2. Paste the cash account detail into 'General Ledger' in the same format.
A7: 3. Enter the closing balances in the yellow cells on the 'Reconciliation' sheet.
A8: 4. Each line is matched on Reference + Amount (COUNTIFS). Unmatched items are classified automatically:
A9: - GL items not on bank: deposits in transit (+) or outstanding cheques (-)
A10: - Bank items not in GL: bank fees, interest, NSF items to be journalized
A11: 5. The status cell turns green and reads RECONCILED when adjusted bank balance = adjusted book balance.
A12: Colour legend: blue text = inputs; black = formulas; yellow fill = cells you fill in.

Sheet Reconciliation
A1: Bank Reconciliation - August 31, 2026
A2: Illustrative sample data for a fictional company. Not from any employer. Built by Tahsin Devrim Mahmud.
A4: BANK SIDE | B4: Amount | D4: BOOK (GL) SIDE | E4: Amount
A5: Balance per bank statement | B5: 90087.22 | D5: Balance per general ledger | E5: 96645.08
A6: Add: deposits in transit | B6: =SUMIFS('General Ledger'!$D$5:$D$200,'General Ledger'!$E$5:$E$200,"No",'General Ledger'!$D$5:$D$200,">0") -> 12388.87 | D6: Add: bank credits not recorded (interest) | E6: =SUMIFS('Bank Statement'!$D$5:$D$200,'Bank Statement'!$E$5:$E$200,"No",'Bank Statement'!$D$5:$D$200,">0") -> 18.62
A7: Less: outstanding cheques | B7: =SUMIFS('General Ledger'!$D$5:$D$200,'General Ledger'!$E$5:$E$200,"No",'General Ledger'!$D$5:$D$200,"<0") -> -7107.39 | D7: Less: bank debits not recorded (fees, NSF) | E7: =SUMIFS('Bank Statement'!$D$5:$D$200,'Bank Statement'!$E$5:$E$200,"No",'Bank Statement'!$D$5:$D$200,"<0") -> -1295
A8: Adjusted bank balance | B8: =SUM(B5:B7) -> 95368.7 | D8: Adjusted book balance | E8: =SUM(E5:E7) -> 95368.7
A10: Difference (should be zero) | B10: =ROUND(B8-E8,2) -> 0 | D10: Status | E10: =IF(B10=0,"RECONCILED","INVESTIGATE") -> RECONCILED
A12: Reconciliation statistics | D12: Journal entries required (book side)
A13: GL items | B13: =COUNTA('General Ledger'!$B$5:$B$200) -> 30 | D13: Dr Bank Service Charges / Cr Cash | E13: =-SUMIFS('Bank Statement'!$D$5:$D$200,'Bank Statement'!$B$5:$B$200,"SVC*",'Bank Statement'!$E$5:$E$200,"No") -> 45
A14: Bank items | B14: =COUNTA('Bank Statement'!$B$5:$B$200) -> 28 | D14: Dr Cash / Cr Interest Income | E14: =SUMIFS('Bank Statement'!$D$5:$D$200,'Bank Statement'!$B$5:$B$200,"INT*",'Bank Statement'!$E$5:$E$200,"No") -> 18.62
A15: Items auto-matched | B15: =COUNTIF('General Ledger'!$E$5:$E$200,"Yes") -> 25 | D15: Dr Accounts Receivable / Cr Cash (NSF) | E15: =-SUMIFS('Bank Statement'!$D$5:$D$200,'Bank Statement'!$B$5:$B$200,"NSF*",'Bank Statement'!$E$5:$E$200,"No") -> 1250
A16: Match rate | B16: =IFERROR(B15/B13,0) -> 0.83333333
A17: Reconciling items to review | B17: =COUNTIF('General Ledger'!$E$5:$E$200,"No")+COUNTIF('Bank Statement'!$E$5:$E$200,"No") -> 8
A19: Notes
A20: Opening balance used to derive closing balances: $48,250.00 (sample assumption).
A21: Matching logic: an item is 'matched' when the same Reference and Amount appear on the other side (COUNTIFS).

Sheet Bank Statement
A1: Bank Statement - August 2026
A2: Illustrative sample data for a fictional company. Not from any employer. Built by Tahsin Devrim Mahmud.
A4: Date | B4: Reference | C4: Description | D4: Amount | E4: Matched?
A5: 46236 | B5: DEP-1001 | C5: Deposit - Maple Leaf Events | D5: 4293.51 | E5: =IF(COUNTIFS('General Ledger'!$B$5:$B$200,B5,'General Ledger'!$D$5:$D$200,D5)>0,"Yes","No") -> Yes
A6: 46237 | B6: CHQ-1002 | C6: Chq - Hydro One | D6: -1809.55 | E6: =IF(COUNTIFS('General Ledger'!$B$5:$B$200,B6,'General Ledger'!$D$5:$D$200,D6)>0,"Yes","No") -> Yes
A7: 46238 | B7: DEP-1003 | C7: Deposit - Summit Dental | D7: 2357.76 | E7: =IF(COUNTIFS('General Ledger'!$B$5:$B$200,B7,'General Ledger'!$D$5:$D$200,D7)>0,"Yes","No") -> Yes
A8: 46239 | B8: CHQ-1004 | C8: Chq - Bell Canada | D8: -621.81 | E8: =IF(COUNTIFS('General Ledger'!$B$5:$B$200,B8,'General Ledger'!$D$5:$D$200,D8)>0,"Yes","No") -> Yes
A9: 46240 | B9: DEP-1005 | C9: Deposit - Summit Dental | D9: 2246.59 | E9: =IF(COUNTIFS('General Ledger'!$B$5:$B$200,B9,'General Ledger'!$D$5:$D$200,D9)>0,"Yes","No") -> Yes
A10: 46241 | B10: CHQ-1006 | C10: Chq - Hydro One | D10: -1098.06 | E10: =IF(COUNTIFS('General Ledger'!$B$5:$B$200,B10,'General Ledger'!$D$5:$D$200,D10)>0,"Yes","No") -> Yes
A11: 46242 | B11: DEP-1007 | C11: Deposit - Northwind Traders | D11: 5139.07 | E11: =IF(COUNTIFS('General Ledger'!$B$5:$B$200,B11,'General Ledger'!$D$5:$D$200,D11)>0,"Yes","No") -> Yes
A12: 46244 | B12: DEP-1009 | C12: Deposit - Summit Dental | D12: 5068.8 | E12: =IF(COUNTIFS('General Ledger'!$B$5:$B$200,B12,'General Ledger'!$D$5:$D$200,D12)>0,"Yes","No") -> Yes
A13: 46245 | B13: CHQ-1010 | C13: Chq - Enbridge Gas | D13: -739.02 | E13: =IF(COUNTIFS('General Ledger'!$B$5:$B$200,B13,'General Ledger'!$D$5:$D$200,D13)>0,"Yes","No") -> Yes
A14: 46246 | B14: DEP-1011 | C14: Deposit - Summit Dental | D14: 6655.82 | E14: =IF(COUNTIFS('General Ledger'!$B$5:$B$200,B14,'General Ledger'!$D$5:$D$200,D14)>0,"Yes","No") -> Yes
A15: 46247 | B15: CHQ-1012 | C15: Chq - Bell Canada | D15: -3993.45 | E15: =IF(COUNTIFS('General Ledger'!$B$5:$B$200,B15,'General Ledger'!$D$5:$D$200,D15)>0,"Yes","No") -> Yes
A16: 46248 | B16: DEP-1013 | C16: Deposit - Northwind Traders | D16: 6308.67 | E16: =IF(COUNTIFS('General Ledger'!$B$5:$B$200,B16,'General Ledger'!$D$5:$D$200,D16)>0,"Yes","No") -> Yes
... A32: 46265 | B32: INT-0831 | C32: Interest earned | D32: 18.62 | E32: =IF(COUNTIFS('General Ledger'!$B$5:$B$200,B32,'General Ledger'!$D$5:$D$200,D32)>0,"Yes","No") -> No
C33: Net activity | D33: =SUM(D5:D32) -> 41837.22

Sheet General Ledger
A1: General Ledger - August 2026
A2: Illustrative sample data for a fictional company. Not from any employer. Built by Tahsin Devrim Mahmud.
A4: Date | B4: Reference | C4: Description | D4: Amount | E4: Matched?
A5: 46235 | B5: DEP-1001 | C5: Deposit - Maple Leaf Events | D5: 4293.51 | E5: =IF(COUNTIFS('Bank Statement'!$B$5:$B$200,B5,'Bank Statement'!$D$5:$D$200,D5)>0,"Yes","No") -> Yes
A6: 46236 | B6: CHQ-1002 | C6: Chq - Hydro One | D6: -1809.55 | E6: =IF(COUNTIFS('Bank Statement'!$B$5:$B$200,B6,'Bank Statement'!$D$5:$D$200,D6)>0,"Yes","No") -> Yes
A7: 46237 | B7: DEP-1003 | C7: Deposit - Summit Dental | D7: 2357.76 | E7: =IF(COUNTIFS('Bank Statement'!$B$5:$B$200,B7,'Bank Statement'!$D$5:$D$200,D7)>0,"Yes","No") -> Yes
A8: 46238 | B8: CHQ-1004 | C8: Chq - Bell Canada | D8: -621.81 | E8: =IF(COUNTIFS('Bank Statement'!$B$5:$B$200,B8,'Bank Statement'!$D$5:$D$200,D8)>0,"Yes","No") -> Yes
A9: 46239 | B9: DEP-1005 | C9: Deposit - Summit Dental | D9: 2246.59 | E9: =IF(COUNTIFS('Bank Statement'!$B$5:$B$200,B9,'Bank Statement'!$D$5:$D$200,D9)>0,"Yes","No") -> Yes
A10: 46240 | B10: CHQ-1006 | C10: Chq - Hydro One | D10: -1098.06 | E10: =IF(COUNTIFS('Bank Statement'!$B$5:$B$200,B10,'Bank Statement'!$D$5:$D$200,D10)>0,"Yes","No") -> Yes
A11: 46241 | B11: DEP-1007 | C11: Deposit - Northwind Traders | D11: 5139.07 | E11: =IF(COUNTIFS('Bank Statement'!$B$5:$B$200,B11,'Bank Statement'!$D$5:$D$200,D11)>0,"Yes","No") -> Yes
A12: 46242 | B12: CHQ-1008 | C12: Chq - Bell Canada | D12: -1200.62 | E12: =IF(COUNTIFS('Bank Statement'!$B$5:$B$200,B12,'Bank Statement'!$D$5:$D$200,D12)>0,"Yes","No") -> No
A13: 46243 | B13: DEP-1009 | C13: Deposit - Summit Dental | D13: 5068.8 | E13: =IF(COUNTIFS('Bank Statement'!$B$5:$B$200,B13,'Bank Statement'!$D$5:$D$200,D13)>0,"Yes","No") -> Yes
A14: 46244 | B14: CHQ-1010 | C14: Chq - Enbridge Gas | D14: -739.02 | E14: =IF(COUNTIFS('Bank Statement'!$B$5:$B$200,B14,'Bank Statement'!$D$5:$D$200,D14)>0,"Yes","No") -> Yes
A15: 46245 | B15: DEP-1011 | C15: Deposit - Summit Dental | D15: 6655.82 | E15: =IF(COUNTIFS('Bank Statement'!$B$5:$B$200,B15,'Bank Statement'!$D$5:$D$200,D15)>0,"Yes","No") -> Yes
A16: 46246 | B16: CHQ-1012 | C16: Chq - Bell Canada | D16: -3993.45 | E16: =IF(COUNTIFS('Bank Statement'!$B$5:$B$200,B16,'Bank Statement'!$D$5:$D$200,D16)>0,"Yes","No") -> Yes
... A34: 46264 | B34: CHQ-1030 | C34: Chq - Bell Canada | D34: -2518.97 | E34: =IF(COUNTIFS('Bank Statement'!$B$5:$B$200,B34,'Bank Statement'!$D$5:$D$200,D34)>0,"Yes","No") -> No
C35: Net activity | D35: =SUM(D5:D34) -> 48395.08
