Workbook

Sheet Audit Dashboard
A1: Daily Revenue & Night Audit Dashboard
A2: TEMPLATE | Created by Tahsin Devrim Mahmud | Contains no real or confidential data
A4: Cash variance tolerance (per day) | H4: HOW TO USE THIS DASHBOARD
H5: SET UP:
A6: MONTH-TO-DATE KPIs | H6: Enter your cash variance tolerance in the yellow cell.
A7: Total revenue | E7: Room revenue | H7: Any day with a larger over / short is flagged on the log.
A8: =SUM('Night Audit Log'!G5:G35) -> 0 | E8: =SUM('Night Audit Log'!D5:D35) -> 0 | H8: DAILY:
A9: Occupancy | E9: ADR (average daily rate) | H9: Complete the Night Audit Log tab for each business day.
A10: =IFERROR(SUM('Night Audit Log'!C5:C35)/SUM('Night Audit Log'!B5:B35),0) -> 0 | E10: =IFERROR(SUM('Night Audit Log'!D5:D35)/SUM('Night Audit Log'!C5:C35),0) -> 0 | H10: Work through the Nightly Close Checklist and mark each step ☑.
A11: RevPAR | E11: Net cash over / (short) | H11: WHAT THE KPIs MEAN:
A12: =IFERROR(SUM('Night Audit Log'!D5:D35)/SUM('Night Audit Log'!B5:B35),0) -> 0 | E12: =SUM('Night Audit Log'!J5:J35) -> 0 | H12: Occupancy shows how full the property was.
A13: Days flagged for investigation | E13: Days audited | H13: ADR shows the average rate earned per occupied room.
A14: =COUNTIF('Night Audit Log'!N5:N35,"INVESTIGATE") -> 0 | E14: =COUNT('Night Audit Log'!A5:A35) -> 0 | H14: RevPAR combines both: room revenue per available room.
H15: Revenue Mix shows each department's share of total revenue.
A16: REVENUE MIX | H16: Days flagged shows how many days need a variance explanation.
A17: Department | C17: Revenue | E17: Share of total | H17: MONTH-END:
A18: Rooms | C18: =SUM('Night Audit Log'!D5:D35) -> 0 | E18: =IFERROR(C18/SUM($C$18:$C$20),0) -> 0 | H18: Save a copy of the workbook, then clear the inputs for the
A19: Food & Beverage | C19: =SUM('Night Audit Log'!E5:E35) -> 0 | E19: =IFERROR(C19/SUM($C$18:$C$20),0) -> 0 | H19: new month. All formulas and formatting stay in place.
A20: Other | C20: =SUM('Night Audit Log'!F5:F35) -> 0 | E20: =IFERROR(C20/SUM($C$18:$C$20),0) -> 0
H21: COLOUR LEGEND
A22: NIGHTLY CLOSE CHECKLIST | H22: Pink column header = you type in this column
A23: Step | C23: Done ☐/☑ | E23: Notes | H23: Navy column header = calculates automatically (do not overwrite)
A24: Balance and count all cashier banks | C24: ☐ | H24: Yellow cell = a setting you choose
A25: Reconcile card settlement batches | C25: ☐ | H25: Green / amber / red highlights = status flags
A26: Post room and tax charges | C26: ☐
A27: Review rate and discount variances | C27: ☐
A28: Match cash deposits to cashier reports | C28: ☐
A29: Document and follow up on variances | C29: ☐
A30: Run and file end-of-day reports | C30: ☐
A31: Sign off the audit pack | C31: ☐
A33: Checklist complete | C33: =IFERROR(COUNTIF(C24:C31,"☑")/COUNTA(A24:A31),0) -> 0

Sheet Night Audit Log
A1: Daily Revenue & Night Audit Log
A2: TEMPLATE | Created by Tahsin Devrim Mahmud | Contains no real or confidential data
A4: Date | B4: Rooms Available | C4: Rooms Sold | D4: Room Revenue | E4: Food & Beverage Revenue | F4: Other Revenue | G4: Total Revenue | H4: Cash Expected | I4: Cash Deposited | J4: Cash Over / (Short) | K4: Occupancy | L4: ADR | M4: RevPAR | N4: Audit Flag | O4: Auditor Initials | Q4: HOW TO USE THE NIGHT AUDIT LOG
G5: =IF(COUNT(D5:F5)=0,"",SUM(D5:F5)) | J5: =IF(OR(H5="",I5=""),"",I5-H5) | K5: =IF(OR(B5="",C5=""),"",IFERROR(C5/B5,"")) | L5: =IF(OR(C5="",D5=""),"",IFERROR(D5/C5,"")) | M5: =IF(OR(B5="",D5=""),"",IFERROR(D5/B5,"")) | N5: =IF(J5="","",IF(ABS(J5)>N('Audit Dashboard'!$C$4),"INVESTIGATE","OK")) | Q5: EACH NIGHT:
G6: =IF(COUNT(D6:F6)=0,"",SUM(D6:F6)) | J6: =IF(OR(H6="",I6=""),"",I6-H6) | K6: =IF(OR(B6="",C6=""),"",IFERROR(C6/B6,"")) | L6: =IF(OR(C6="",D6=""),"",IFERROR(D6/C6,"")) | M6: =IF(OR(B6="",D6=""),"",IFERROR(D6/B6,"")) | N6: =IF(J6="","",IF(ABS(J6)>N('Audit Dashboard'!$C$4),"INVESTIGATE","OK")) | Q6: Add one row per business day and enter the date.
G7: =IF(COUNT(D7:F7)=0,"",SUM(D7:F7)) | J7: =IF(OR(H7="",I7=""),"",I7-H7) | K7: =IF(OR(B7="",C7=""),"",IFERROR(C7/B7,"")) | L7: =IF(OR(C7="",D7=""),"",IFERROR(D7/C7,"")) | M7: =IF(OR(B7="",D7=""),"",IFERROR(D7/B7,"")) | N7: =IF(J7="","",IF(ABS(J7)>N('Audit Dashboard'!$C$4),"INVESTIGATE","OK")) | Q7: Enter rooms available and rooms sold from the property system.
G8: =IF(COUNT(D8:F8)=0,"",SUM(D8:F8)) | J8: =IF(OR(H8="",I8=""),"",I8-H8) | K8: =IF(OR(B8="",C8=""),"",IFERROR(C8/B8,"")) | L8: =IF(OR(C8="",D8=""),"",IFERROR(D8/C8,"")) | M8: =IF(OR(B8="",D8=""),"",IFERROR(D8/B8,"")) | N8: =IF(J8="","",IF(ABS(J8)>N('Audit Dashboard'!$C$4),"INVESTIGATE","OK")) | Q8: Enter revenue by department: rooms, food & beverage, other.
G9: =IF(COUNT(D9:F9)=0,"",SUM(D9:F9)) | J9: =IF(OR(H9="",I9=""),"",I9-H9) | K9: =IF(OR(B9="",C9=""),"",IFERROR(C9/B9,"")) | L9: =IF(OR(C9="",D9=""),"",IFERROR(D9/C9,"")) | M9: =IF(OR(B9="",D9=""),"",IFERROR(D9/B9,"")) | N9: =IF(J9="","",IF(ABS(J9)>N('Audit Dashboard'!$C$4),"INVESTIGATE","OK")) | Q9: Enter cash expected (from the cashier reports) and cash deposited.
G10: =IF(COUNT(D10:F10)=0,"",SUM(D10:F10)) | J10: =IF(OR(H10="",I10=""),"",I10-H10) | K10: =IF(OR(B10="",C10=""),"",IFERROR(C10/B10,"")) | L10: =IF(OR(C10="",D10=""),"",IFERROR(D10/C10,"")) | M10: =IF(OR(B10="",D10=""),"",IFERROR(D10/B10,"")) | N10: =IF(J10="","",IF(ABS(J10)>N('Audit Dashboard'!$C$4),"INVESTIGATE","OK")) | Q10: Add your initials so every audit day has an owner.
G11: =IF(COUNT(D11:F11)=0,"",SUM(D11:F11)) | J11: =IF(OR(H11="",I11=""),"",I11-H11) | K11: =IF(OR(B11="",C11=""),"",IFERROR(C11/B11,"")) | L11: =IF(OR(C11="",D11=""),"",IFERROR(D11/C11,"")) | M11: =IF(OR(B11="",D11=""),"",IFERROR(D11/B11,"")) | N11: =IF(J11="","",IF(ABS(J11)>N('Audit Dashboard'!$C$4),"INVESTIGATE","OK")) | Q11: WHAT CALCULATES AUTOMATICALLY:
G12: =IF(COUNT(D12:F12)=0,"",SUM(D12:F12)) | J12: =IF(OR(H12="",I12=""),"",I12-H12) | K12: =IF(OR(B12="",C12=""),"",IFERROR(C12/B12,"")) | L12: =IF(OR(C12="",D12=""),"",IFERROR(D12/C12,"")) | M12: =IF(OR(B12="",D12=""),"",IFERROR(D12/B12,"")) | N12: =IF(J12="","",IF(ABS(J12)>N('Audit Dashboard'!$C$4),"INVESTIGATE","OK")) | Q12: Total Revenue = rooms + food & beverage + other revenue.
G13: =IF(COUNT(D13:F13)=0,"",SUM(D13:F13)) | J13: =IF(OR(H13="",I13=""),"",I13-H13) | K13: =IF(OR(B13="",C13=""),"",IFERROR(C13/B13,"")) | L13: =IF(OR(C13="",D13=""),"",IFERROR(D13/C13,"")) | M13: =IF(OR(B13="",D13=""),"",IFERROR(D13/B13,"")) | N13: =IF(J13="","",IF(ABS(J13)>N('Audit Dashboard'!$C$4),"INVESTIGATE","OK")) | Q13: Cash Over / (Short) = cash deposited minus cash expected.
G14: =IF(COUNT(D14:F14)=0,"",SUM(D14:F14)) | J14: =IF(OR(H14="",I14=""),"",I14-H14) | K14: =IF(OR(B14="",C14=""),"",IFERROR(C14/B14,"")) | L14: =IF(OR(C14="",D14=""),"",IFERROR(D14/C14,"")) | M14: =IF(OR(B14="",D14=""),"",IFERROR(D14/B14,"")) | N14: =IF(J14="","",IF(ABS(J14)>N('Audit Dashboard'!$C$4),"INVESTIGATE","OK")) | Q14: Occupancy = rooms sold divided by rooms available.
G15: =IF(COUNT(D15:F15)=0,"",SUM(D15:F15)) | J15: =IF(OR(H15="",I15=""),"",I15-H15) | K15: =IF(OR(B15="",C15=""),"",IFERROR(C15/B15,"")) | L15: =IF(OR(C15="",D15=""),"",IFERROR(D15/C15,"")) | M15: =IF(OR(B15="",D15=""),"",IFERROR(D15/B15,"")) | N15: =IF(J15="","",IF(ABS(J15)>N('Audit Dashboard'!$C$4),"INVESTIGATE","OK")) | Q15: ADR (average daily rate) = room revenue divided by rooms sold.
G16: =IF(COUNT(D16:F16)=0,"",SUM(D16:F16)) | J16: =IF(OR(H16="",I16=""),"",I16-H16) | K16: =IF(OR(B16="",C16=""),"",IFERROR(C16/B16,"")) | L16: =IF(OR(C16="",D16=""),"",IFERROR(D16/C16,"")) | M16: =IF(OR(B16="",D16=""),"",IFERROR(D16/B16,"")) | N16: =IF(J16="","",IF(ABS(J16)>N('Audit Dashboard'!$C$4),"INVESTIGATE","OK")) | Q16: RevPAR = room revenue divided by rooms available.
... G21: =IF(COUNT(D21:F21)=0,"",SUM(D21:F21)) | J21: =IF(OR(H21="",I21=""),"",I21-H21) | K21: =IF(OR(B21="",C21=""),"",IFERROR(C21/B21,"")) | L21: =IF(OR(C21="",D21=""),"",IFERROR(D21/C21,"")) | M21: =IF(OR(B21="",D21=""),"",IFERROR(D21/B21,"")) | N21: =IF(J21="","",IF(ABS(J21)>N('Audit Dashboard'!$C$4),"INVESTIGATE","OK")) | Q21: document the cause and follow-up before closing the day.
G22: =IF(COUNT(D22:F22)=0,"",SUM(D22:F22)) | J22: =IF(OR(H22="",I22=""),"",I22-H22) | K22: =IF(OR(B22="",C22=""),"",IFERROR(C22/B22,"")) | L22: =IF(OR(C22="",D22=""),"",IFERROR(D22/C22,"")) | M22: =IF(OR(B22="",D22=""),"",IFERROR(D22/B22,"")) | N22: =IF(J22="","",IF(ABS(J22)>N('Audit Dashboard'!$C$4),"INVESTIGATE","OK"))
G23: =IF(COUNT(D23:F23)=0,"",SUM(D23:F23)) | J23: =IF(OR(H23="",I23=""),"",I23-H23) | K23: =IF(OR(B23="",C23=""),"",IFERROR(C23/B23,"")) | L23: =IF(OR(C23="",D23=""),"",IFERROR(D23/C23,"")) | M23: =IF(OR(B23="",D23=""),"",IFERROR(D23/B23,"")) | N23: =IF(J23="","",IF(ABS(J23)>N('Audit Dashboard'!$C$4),"INVESTIGATE","OK")) | Q23: COLOUR LEGEND
G24: =IF(COUNT(D24:F24)=0,"",SUM(D24:F24)) | J24: =IF(OR(H24="",I24=""),"",I24-H24) | K24: =IF(OR(B24="",C24=""),"",IFERROR(C24/B24,"")) | L24: =IF(OR(C24="",D24=""),"",IFERROR(D24/C24,"")) | M24: =IF(OR(B24="",D24=""),"",IFERROR(D24/B24,"")) | N24: =IF(J24="","",IF(ABS(J24)>N('Audit Dashboard'!$C$4),"INVESTIGATE","OK")) | Q24: Pink column header = you type in this column
G25: =IF(COUNT(D25:F25)=0,"",SUM(D25:F25)) | J25: =IF(OR(H25="",I25=""),"",I25-H25) | K25: =IF(OR(B25="",C25=""),"",IFERROR(C25/B25,"")) | L25: =IF(OR(C25="",D25=""),"",IFERROR(D25/C25,"")) | M25: =IF(OR(B25="",D25=""),"",IFERROR(D25/B25,"")) | N25: =IF(J25="","",IF(ABS(J25)>N('Audit Dashboard'!$C$4),"INVESTIGATE","OK")) | Q25: Navy column header = calculates automatically (do not overwrite)
G26: =IF(COUNT(D26:F26)=0,"",SUM(D26:F26)) | J26: =IF(OR(H26="",I26=""),"",I26-H26) | K26: =IF(OR(B26="",C26=""),"",IFERROR(C26/B26,"")) | L26: =IF(OR(C26="",D26=""),"",IFERROR(D26/C26,"")) | M26: =IF(OR(B26="",D26=""),"",IFERROR(D26/B26,"")) | N26: =IF(J26="","",IF(ABS(J26)>N('Audit Dashboard'!$C$4),"INVESTIGATE","OK")) | Q26: Yellow cell = a setting you choose
G27: =IF(COUNT(D27:F27)=0,"",SUM(D27:F27)) | J27: =IF(OR(H27="",I27=""),"",I27-H27) | K27: =IF(OR(B27="",C27=""),"",IFERROR(C27/B27,"")) | L27: =IF(OR(C27="",D27=""),"",IFERROR(D27/C27,"")) | M27: =IF(OR(B27="",D27=""),"",IFERROR(D27/B27,"")) | N27: =IF(J27="","",IF(ABS(J27)>N('Audit Dashboard'!$C$4),"INVESTIGATE","OK")) | Q27: Green / amber / red highlights = status flags
G28: =IF(COUNT(D28:F28)=0,"",SUM(D28:F28)) | J28: =IF(OR(H28="",I28=""),"",I28-H28) | K28: =IF(OR(B28="",C28=""),"",IFERROR(C28/B28,"")) | L28: =IF(OR(C28="",D28=""),"",IFERROR(D28/C28,"")) | M28: =IF(OR(B28="",D28=""),"",IFERROR(D28/B28,"")) | N28: =IF(J28="","",IF(ABS(J28)>N('Audit Dashboard'!$C$4),"INVESTIGATE","OK"))
G29: =IF(COUNT(D29:F29)=0,"",SUM(D29:F29)) | J29: =IF(OR(H29="",I29=""),"",I29-H29) | K29: =IF(OR(B29="",C29=""),"",IFERROR(C29/B29,"")) | L29: =IF(OR(C29="",D29=""),"",IFERROR(D29/C29,"")) | M29: =IF(OR(B29="",D29=""),"",IFERROR(D29/B29,"")) | N29: =IF(J29="","",IF(ABS(J29)>N('Audit Dashboard'!$C$4),"INVESTIGATE","OK"))
G30: =IF(COUNT(D30:F30)=0,"",SUM(D30:F30)) | J30: =IF(OR(H30="",I30=""),"",I30-H30) | K30: =IF(OR(B30="",C30=""),"",IFERROR(C30/B30,"")) | L30: =IF(OR(C30="",D30=""),"",IFERROR(D30/C30,"")) | M30: =IF(OR(B30="",D30=""),"",IFERROR(D30/B30,"")) | N30: =IF(J30="","",IF(ABS(J30)>N('Audit Dashboard'!$C$4),"INVESTIGATE","OK"))
G31: =IF(COUNT(D31:F31)=0,"",SUM(D31:F31)) | J31: =IF(OR(H31="",I31=""),"",I31-H31) | K31: =IF(OR(B31="",C31=""),"",IFERROR(C31/B31,"")) | L31: =IF(OR(C31="",D31=""),"",IFERROR(D31/C31,"")) | M31: =IF(OR(B31="",D31=""),"",IFERROR(D31/B31,"")) | N31: =IF(J31="","",IF(ABS(J31)>N('Audit Dashboard'!$C$4),"INVESTIGATE","OK"))
G32: =IF(COUNT(D32:F32)=0,"",SUM(D32:F32)) | J32: =IF(OR(H32="",I32=""),"",I32-H32) | K32: =IF(OR(B32="",C32=""),"",IFERROR(C32/B32,"")) | L32: =IF(OR(C32="",D32=""),"",IFERROR(D32/C32,"")) | M32: =IF(OR(B32="",D32=""),"",IFERROR(D32/B32,"")) | N32: =IF(J32="","",IF(ABS(J32)>N('Audit Dashboard'!$C$4),"INVESTIGATE","OK"))
G33: =IF(COUNT(D33:F33)=0,"",SUM(D33:F33)) | J33: =IF(OR(H33="",I33=""),"",I33-H33) | K33: =IF(OR(B33="",C33=""),"",IFERROR(C33/B33,"")) | L33: =IF(OR(C33="",D33=""),"",IFERROR(D33/C33,"")) | M33: =IF(OR(B33="",D33=""),"",IFERROR(D33/B33,"")) | N33: =IF(J33="","",IF(ABS(J33)>N('Audit Dashboard'!$C$4),"INVESTIGATE","OK"))
G34: =IF(COUNT(D34:F34)=0,"",SUM(D34:F34)) | J34: =IF(OR(H34="",I34=""),"",I34-H34) | K34: =IF(OR(B34="",C34=""),"",IFERROR(C34/B34,"")) | L34: =IF(OR(C34="",D34=""),"",IFERROR(D34/C34,"")) | M34: =IF(OR(B34="",D34=""),"",IFERROR(D34/B34,"")) | N34: =IF(J34="","",IF(ABS(J34)>N('Audit Dashboard'!$C$4),"INVESTIGATE","OK"))
G35: =IF(COUNT(D35:F35)=0,"",SUM(D35:F35)) | J35: =IF(OR(H35="",I35=""),"",I35-H35) | K35: =IF(OR(B35="",C35=""),"",IFERROR(C35/B35,"")) | L35: =IF(OR(C35="",D35=""),"",IFERROR(D35/C35,"")) | M35: =IF(OR(B35="",D35=""),"",IFERROR(D35/B35,"")) | N35: =IF(J35="","",IF(ABS(J35)>N('Audit Dashboard'!$C$4),"INVESTIGATE","OK"))
